xthematic/__init__.py
xthematic/__version__.py
xthematic/cli.py
xthematic/colors.py
xthematic/config.py
xthematic/display.py
xthematic/term.py
xthematic/themes.py
xthematic-0.0.3.dist-info/METADATA
xthematic-0.0.3.dist-info/RECORD
xthematic-0.0.3.dist-info/WHEEL
xthematic-0.0.3.dist-info/entry_points.txt
xthematic-0.0.3.dist-info/top_level.txt
