Metadata-Version: 2.1
Name: xthematic
Version: 0.0.3
Summary: cli app for customizing terminals
Home-page: https://github.com/taesko/xthematic
Author: Antonio Todorov
Author-email: taeskow@gmail.com
License: MIT
Keywords: cli application terminal emulator theme customize X XResources
Platform: UNKNOWN
Classifier: Development Status :: 3 - Alpha
Classifier: Environment :: Console
Classifier: Framework :: Pytest
Classifier: Intended Audience :: End Users/Desktop
Classifier: License :: OSI Approved :: MIT License
Classifier: Operating System :: POSIX :: Linux
Classifier: Programming Language :: Python
Classifier: Programming Language :: Python :: 3
Classifier: Programming Language :: Python :: 3.6
Classifier: Programming Language :: Python :: Implementation :: CPython
Classifier: Topic :: Terminals :: Terminal Emulators/X Terminals
Classifier: Topic :: Utilities
Requires-Python: >=3.6.0
Requires-Dist: click
Requires-Dist: xparser (>=0.0.4)
Requires-Dist: sty
